arches_controlled_lists/__init__.py
arches_controlled_lists/apps.py
arches_controlled_lists/celery.py
arches_controlled_lists/hosts.py
arches_controlled_lists/models.py
arches_controlled_lists/querysets.py
arches_controlled_lists/settings.py
arches_controlled_lists/settings_local.py
arches_controlled_lists/sql_config.py
arches_controlled_lists/urls.py
arches_controlled_lists/views.py
arches_controlled_lists/wsgi.py
arches_controlled_lists/datatypes/__init__.py
arches_controlled_lists/datatypes/datatypes.py
arches_controlled_lists/functions/__init__.py
arches_controlled_lists/locale/.gitkeep
arches_controlled_lists/locale/messages.pot
arches_controlled_lists/management/__init__.py
arches_controlled_lists/management/commands/__init__.py
arches_controlled_lists/management/commands/controlled_lists.py
arches_controlled_lists/management/commands/packages.py
arches_controlled_lists/media/css/themes/_project.scss
arches_controlled_lists/media/img/favicon.png
arches_controlled_lists/media/js/viewmodels/reference-select.js
arches_controlled_lists/media/js/views/components/datatypes/reference.js
arches_controlled_lists/media/js/views/components/plugins/controlled-list-manager.js
arches_controlled_lists/media/js/views/components/widgets/reference-select.js
arches_controlled_lists/migrations/0001_initial.py
arches_controlled_lists/migrations/0002_etl_collections_to_controlled_lists.py
arches_controlled_lists/migrations/0003_rename_search_only_list_searchable.py
arches_controlled_lists/migrations/0004_reconfigure_listitem_sortorder_constraints.py
arches_controlled_lists/migrations/0005_add_reference_select_widget_mapping.py
arches_controlled_lists/migrations/0006_update_spatial_view_reference_type.py
arches_controlled_lists/migrations/0007_change_listitemvalue_value_from_char_to_text_field.py
arches_controlled_lists/migrations/0008_ensure_languages_in_sync.py
arches_controlled_lists/migrations/0009_reconfigure_migration_for_polyhierarchies.py
arches_controlled_lists-1.0.1.dist-info/licenses/LICENSE
arches_controlled_lists-1.0.1.dist-info/METADATA
arches_controlled_lists-1.0.1.dist-info/WHEEL
arches_controlled_lists-1.0.1.dist-info/top_level.txt
arches_controlled_lists-1.0.1.dist-info/RECORD
