Metadata-Version: 2.4
Name: arches-controlled-lists
Version: 1.0.1
Summary: An Arches application designed to manage controlled lists and reference data within the Arches platform.
Author: Arches Project
License-Expression: AGPL-3.0-or-later
Project-URL: Homepage, https://archesproject.org/
Project-URL: Documentation, https://arches.readthedocs.io
Project-URL: Repository, https://github.com/archesproject/arches-controlled-lists.git
Project-URL: Issues, https://github.com/archesproject/arches-controlled-lists/issues
Classifier: Development Status :: 5 - Production/Stable
Classifier: Programming Language :: Python
Classifier: Programming Language :: Python :: 3
Classifier: Programming Language :: Python :: 3 :: Only
Classifier: Programming Language :: Python :: 3.11
Classifier: Programming Language :: Python :: 3.12
Classifier: Programming Language :: Python :: 3.13
Classifier: Framework :: Django
Classifier: Framework :: Django :: 5.2
Classifier: Intended Audience :: Developers
Classifier: Intended Audience :: Science/Research
Classifier: Intended Audience :: Information Technology
Requires-Python: >=3.11
License-File: LICENSE
Requires-Dist: arches>=8.0.1
Requires-Dist: arches_component_lab==0.0.1a3
Dynamic: license-file
